[
  {
    "name": "should return home page",
    "summary": "should return home page",
    "hierarchy": [
      "Asdeporte miscroservice Test",
      "should return home page"
    ],
    "request": {
      "headers": {},
      "method": "GET",
      "path": "/"
    },
    "response": {
      "status": 200,
      "headers": {
        "content-type": "application/json; charset=utf-8"
      },
      "body": {
        "error": false,
        "version": "1.0.0",
        "message": "Asdeporte microservice scaffold",
        "cassandra": true
      }
    },
    "snippets": {
      "curl": "curl -X GET \"https://api.asdeporte.com/\""
    },
    "id": 0
  }
]